[
    {
        "bookId": "30056764",
        "bookLink": "https://www.goodreads.com/book/show/30056764-ng-i-tr-ng-ng",
        "bookTitle": "Người Trông Đồng",
        "bookRate": "4.00",
        "bookDescription": "Cuốn sách nhỏ được xuất bản như một món quà dành tặng người thân và bằng hữu. Thế nhưng những gì hai truyện ngắn Người trông đồng và Tháng Mười mang đến lại thực sự không nhỏ. Trên nền cốt truyện dường như không có gì mới, một văn phong mượt mà tuôn chảy tựa như những áng văn cổ điển, đẹp một cách mẫu mực. Người trông đồng, một câu chuyện không có cốt chuyện, miên man như \nCuốn sách nhỏ được xuất bản như một món quà dành tặng người thân và bằng hữu. Thế nhưng những gì hai truyện ngắn Người trông đồng và Tháng Mười mang đến lại thực sự không nhỏ. Trên nền cốt truyện dường như không có gì mới, một văn phong mượt mà tuôn chảy tựa như những áng văn cổ điển, đẹp một cách mẫu mực. Người trông đồng, một câu chuyện không có cốt chuyện, miên man như đời sống, ẩn chứa một triết lý riêng tây của con người cô đơn giữa đồng hoang, nghĩa địa. Tháng Mười lại khác, một câu chuyện tình đan xen khéo léo giữa thực tại và quá khứ, thấm thía buồn – vui, đi vào tận đáy linh hồn của tình yêu muôn thuở, làm mới mẻ, lay động bất tận điều tưởng chừng đã cũ. Một cuốn sách không thể bỏ qua đối với những người yêu mến văn chương.\n...more",
        "bookReviews": {
            "userId": [
                "36284265",
                "67253117",
                "53433900",
                "46296321",
                "42259367",
                "35178216",
                "56126995",
                "47070655",
                "82854098",
                "52634710",
                "88272653",
                "43079623",
                "82626146",
                "18446231",
                "70089371",
                "76884783",
                "93104285",
                "98000044",
                "96659094",
                "110792922",
                "107550525",
                "64225585"
            ],
            "userName": [
                "Jang Nguyễn",
                "Kido",
                "Thu Thao",
                "Nguyễn Quang Vũ",
                "Huyền Trang",
                "Called",
                "Hèm Tẹt",
                "선 하",
                "Ly Huỳnh",
                "Thuy Tien",
                "Duy Phan",
                "tae prince ♥",
                "Linh Dương",
                "Xuan",
                "Đan Trần",
                "Tu Do Thu Ha",
                "Jenny Jowie",
                "phuong191",
                "Lê Hiếu",
                "Bi Bi",
                "Linh Nguyen",
                "Quỳnh Quỳnh"
            ],
            "rate": [
                4,
                0,
                0,
                0,
                0,
                0,
                0,
                0,
                0,
                0,
                0,
                0,
                0,
                0,
                0,
                0,
                0,
                0,
                0,
                0,
                0,
                0
            ],
            "contentReview": [
                "\"Có cái gì đó thật vô nhân và ghê sợ khi con người ta phải nằm trong đất lạnh, bị bỏ mặt một mình cho sâu bọ và tăm tối. Đối với tôi, điều đó thật khủng khiếp và còn tệ hại hơn bản thân cái chết. Điều gì sẽ xảy ra nếu như những kẻ đã từng là người chợt thức tỉnh và nhận ra mình đang ở đâu và vùng dậy? Có kẻ nào lại thức dậy từ cái chết? Thật rùng rợn mỗi khi nghĩ đến điều đó. Thế mà trí não thì chỉ nghĩ được có vậy. Hơn thế nữa, dường như với trí não chỉ duy có điều đó là sự thật và đó là tất cả\n\"Có cái gì đó thật vô nhân và ghê sợ khi con người ta phải nằm trong đất lạnh, bị bỏ mặt một mình cho sâu bọ và tăm tối. Đối với tôi, điều đó thật khủng khiếp và còn tệ hại hơn bản thân cái chết. Điều gì sẽ xảy ra nếu như những kẻ đã từng là người chợt thức tỉnh và nhận ra mình đang ở đâu và vùng dậy? Có kẻ nào lại thức dậy từ cái chết? Thật rùng rợn mỗi khi nghĩ đến điều đó. Thế mà trí não thì chỉ nghĩ được có vậy. Hơn thế nữa, dường như với trí não chỉ duy có điều đó là sự thật và đó là tất cả kiến thức nó biết về cái chết. Khi thân thể ta tan rữa thì tinh thần cũng mất theo. Mất một cách bí mật. Không dấu vết. Khi ta chết thì thế giới này chắc chắn sẽ tắt phụt. Đèn không còn thì tất cả sẽ chìm trong bóng tối. Khi đó có lẽ là hư vô. Nhưng mà ta không thể cảm thấy được. Vì ta đâu còn nữa.\"_Người trông đồng - trang 23_\n...more",
                "",
                "",
                "",
                "",
                "",
                "",
                "",
                "",
                "",
                "",
                "",
                "",
                "",
                "",
                "",
                "",
                "",
                "",
                "",
                "",
                ""
            ],
            "commentList": [
                "https://www.goodreads.com//review/show/1624186643?book_show_action=true&from_review_page=1",
                "",
                "",
                "",
                "",
                "",
                "",
                "",
                "",
                "",
                "",
                "",
                "",
                "",
                "",
                "",
                "",
                "",
                "",
                "",
                "",
                ""
            ],
            "datePost": [
                "Apr 29, 2016",
                "May 04, 2017",
                "Jan 17, 2018",
                "Jun 11, 2020",
                "May 05, 2016",
                "Jul 06, 2016",
                "Dec 25, 2016",
                "Mar 21, 2017",
                "Aug 25, 2018",
                "Oct 19, 2018",
                "Oct 20, 2018",
                "Nov 07, 2018",
                "Jan 04, 2019",
                "May 05, 2019",
                "May 24, 2019",
                "May 27, 2019",
                "Jun 24, 2019",
                "Jun 25, 2019",
                "Jan 25, 2020",
                "Feb 29, 2020",
                "Jul 09, 2020",
                "Jun 11, 2020"
            ]
        }
    },
    {
        "bookId": "30652844",
        "bookLink": "https://www.goodreads.com/book/show/30652844-m-a-h-b-n-r-n",
        "bookTitle": "Mùa Hè Bận Rộn (Kính Vạn Hoa #21)",
        "bookRate": "4.00",
        "bookDescription": "",
        "bookReviews": {
            "userId": [
                "96547666",
                "67253117",
                "12670794",
                "28139223",
                "34028181",
                "71509851",
                "78940350",
                "82626146",
                "70089371",
                "76884783",
                "93384629",
                "98000044",
                "69271750",
                "88215245",
                "88252354",
                "119888778",
                "86481453"
            ],
            "userName": [
                "Lê Ngọc Nguyên Phương",
                "Kido",
                "Khuu Bao",
                "Ngoc Mai Anh Dao ",
                "Ann",
                "Mia Duong",
                "Nthongyen",
                "Linh Dương",
                "Đan Trần",
                "Tu Do Thu Ha",
                "bong",
                "phuong191",
                "Dang Minh Ngoc",
                "Hoang Hien",
                "Lê Phan Quỳnh",
                "Pham Nhat Quang",
                "ducnguyen"
            ],
            "rate": [
                0,
                0,
                0,
                0,
                0,
                0,
                0,
                0,
                0,
                0,
                0,
                0,
                0,
                0,
                0,
                0,
                0
            ],
            "contentReview": [
                "",
                "",
                "",
                "",
                "",
                "",
                "",
                "",
                "",
                "",
                "",
                "",
                "",
                "",
                "",
                "",
                ""
            ],
            "commentList": [
                "",
                "",
                "",
                "",
                "",
                "",
                "",
                "",
                "",
                "",
                "",
                "",
                "",
                "",
                "",
                "",
                ""
            ],
            "datePost": [
                "Aug 12, 2020",
                "May 04, 2017",
                "Mar 17, 2020",
                "Jun 19, 2016",
                "Aug 04, 2016",
                "Nov 23, 2017",
                "Mar 08, 2018",
                "Jan 04, 2019",
                "May 24, 2019",
                "May 27, 2019",
                "Jun 08, 2019",
                "Jun 26, 2019",
                "Jan 31, 2020",
                "Mar 10, 2020",
                "Jun 09, 2020",
                "Aug 14, 2020",
                "Sep 08, 2020"
            ]
        }
    }
]